garageops/__about__.py
garageops/__init__.py
garageops/__main__.py
garageops/cli.py
garageops-0.0.1.dist-info/METADATA
garageops-0.0.1.dist-info/WHEEL
garageops-0.0.1.dist-info/entry_points.txt
garageops-0.0.1.dist-info/RECORD
