Metadata-Version: 2.1
Name: garageops
Version: 0.0.1
Summary: Garage Ops
Project-URL: Homepage, https://github.com/garageops/garageops
Project-URL: Issues, https://github.com/garageops/garageops/issues
Author-email: Chris Wilson <christopher.david.wilson@gmail.com>
Classifier: License :: OSI Approved :: MIT License
Classifier: Operating System :: OS Independent
Classifier: Programming Language :: Python :: 3
Requires-Python: >=3.10
Requires-Dist: typer[all]
Provides-Extra: dev
Requires-Dist: pytest; extra == 'dev'
